deb_parse/__init__.py
deb_parse/parser.py
deb_parse-0.1.1.dist-info/LICENSE.txt
deb_parse-0.1.1.dist-info/METADATA
deb_parse-0.1.1.dist-info/WHEEL
deb_parse-0.1.1.dist-info/top_level.txt
deb_parse-0.1.1.dist-info/RECORD
