Metadata-Version: 2.1
Name: deb-parse
Version: 0.1.1
Summary: Parses Debian Control-File formats.
Home-page: https://github.com/aihaddad/deb-parse.git
Author: Ahmed Elhaddad
Author-email: aihaddad@outlook.com
License: MIT
Platform: UNKNOWN
Classifier: License :: OSI Approved :: MIT License
Classifier: Programming Language :: Python
Classifier: Programming Language :: Python :: 3
Classifier: Programming Language :: Python :: 3.7
Classifier: Programming Language :: Python :: Implementation :: CPython
Classifier: Programming Language :: Python :: Implementation :: PyPy
Requires-Python: >=3.7.0
